resync_simulator-1.1.0.data/scripts/resync-simulator
simulator/__init__.py
simulator/_version.py
simulator/changememory.py
simulator/http.py
simulator/observer.py
simulator/resource.py
simulator/source.py
simulator/static/favicon.ico
simulator/static/resourcesync.css
simulator/templates/base.html
simulator/templates/home.html
simulator/templates/resource.index.html
resync_simulator-1.1.0.dist-info/METADATA
resync_simulator-1.1.0.dist-info/WHEEL
resync_simulator-1.1.0.dist-info/top_level.txt
resync_simulator-1.1.0.dist-info/RECORD
