Metadata-Version: 2.1
Name: resync-simulator
Version: 1.1.0
Summary: ResourceSync source simulator
Home-page: http://github.com/resync/resync-simulator
Author: Bernhard Haslhofer
Author-email: bernhard.haslhofer@univie.ac.at
License: Creative Commons Attribution-Noncommercial-Share Alike license
Platform: UNKNOWN
Classifier: Development Status :: 4 - Beta
Classifier: Intended Audience :: Developers
Classifier: Operating System :: OS Independent
Classifier: Programming Language :: Python
Classifier: Programming Language :: Python :: 3.5
Classifier: Programming Language :: Python :: 3.6
Classifier: Programming Language :: Python :: 3.7
Classifier: Programming Language :: Python :: 3.8
Classifier: Topic :: Internet :: WWW/HTTP
Classifier: Environment :: Web Environment
